pyxelart_detector/__init__.py
pyxelart_detector/__main__.py
pyxelart_detector/pyxelart_detector.py
pyxelart_detector/test.py
pyxelart_detector-0.1.3.dist-info/METADATA
pyxelart_detector-0.1.3.dist-info/WHEEL
pyxelart_detector-0.1.3.dist-info/entry_points.txt
pyxelart_detector-0.1.3.dist-info/licenses/LICENSE
pyxelart_detector-0.1.3.dist-info/RECORD
