Metadata-Version: 2.4
Name: pyxelart-detector
Version: 0.1.3
Summary: A library to detect if an image is likely pixel art.
Project-URL: Repository, https://github.com/dann-merlin/pyxelart-detector
Project-URL: Issues, https://github.com/dann-merlin/pyxelart-detector/issues
Author-email: Merlin Sievers <merlin.sievers@posteo.net>
License: AGPL-3.0-or-later
License-File: LICENSE
Classifier: Operating System :: OS Independent
Classifier: Programming Language :: Python :: 3
Classifier: Programming Language :: Python :: 3.13
Classifier: Topic :: Scientific/Engineering :: Image Processing
Classifier: Topic :: Scientific/Engineering :: Image Recognition
Requires-Python: >=3.13
Requires-Dist: matplotlib>=3.10.0
Requires-Dist: mpl-interactions>=0.24.2
Requires-Dist: pillow>=11.1.0
Requires-Dist: pyqt6>=6.8.1
Requires-Dist: scikit-image>=0.25.1
Requires-Dist: scipy>=1.15.2
Requires-Dist: termcolor>=2.5.0
